ttl_cache.py
ttl_cache-1.6.dist-info/METADATA
ttl_cache-1.6.dist-info/WHEEL
ttl_cache-1.6.dist-info/top_level.txt
ttl_cache-1.6.dist-info/RECORD
