Metadata-Version: 2.1
Name: ttl-cache
Version: 1.6
Summary: Decorator to wrap a function with a memoizing callable that has TTL result
Home-page: https://github.com/lwzm/ttl-cache
Author: lwzm
Author-email: lwzm@qq.com
License: UNKNOWN
Keywords: cache,ttl,decorator,functools
Platform: UNKNOWN
Classifier: Environment :: Console
Classifier: Programming Language :: Python :: 2.7
Classifier: Programming Language :: Python :: 3
Classifier: Programming Language :: Python :: 3.6
Classifier: Programming Language :: Python :: 3.7
Classifier: Programming Language :: Python :: Implementation :: CPython
Classifier: Programming Language :: Python :: Implementation :: PyPy
Classifier: Topic :: Software Development :: Libraries :: Python Modules
Classifier: License :: OSI Approved :: MIT License
